github_issue_creator/__init__.py
github_issue_creator/github_issue_creator.py
github_issue_creator/exceptions/__init__.py
github_issue_creator/exceptions/exceptions.py
github_issue_creator/models/__init__.py
github_issue_creator/models/issue.py
github_issue_creator/models/issue_response.py
github_issue_creator-0.2.2.dist-info/licenses/LICENSE
github_issue_creator-0.2.2.dist-info/METADATA
github_issue_creator-0.2.2.dist-info/WHEEL
github_issue_creator-0.2.2.dist-info/top_level.txt
github_issue_creator-0.2.2.dist-info/RECORD
