Metadata-Version: 2.4
Name: github-issue-creator
Version: 0.2.2
Summary: A Python library for creating GitHub issues programmatically using the GitHub REST API.
Author-email: Bruno Peselli <brunopeselli@gmail.com>
License: Copyright 2025 Bruno Peselli
Project-URL: homepage, https://github.com/pzzzl/github_issue_creator
License-File: LICENSE
Requires-Dist: requests
Requires-Dist: pydantic==2.11.5
Dynamic: license-file
